DHEater-0.4.3.data/scripts/dh_param_priv_key_size_setter
dheater/__main__.py
dheater/__setup__.py
DHEater-0.4.3.dist-info/LICENSE.txt
DHEater-0.4.3.dist-info/METADATA
DHEater-0.4.3.dist-info/WHEEL
DHEater-0.4.3.dist-info/entry_points.txt
DHEater-0.4.3.dist-info/top_level.txt
DHEater-0.4.3.dist-info/RECORD
