Metadata-Version: 2.1
Name: DHEater
Version: 0.4.3
Summary: D(HE)ater is an attacking tool heating the CPU by enforcing DHE KEX in case of TLS and SSH
Home-page: https://gitlab.com/dheatattack/dheater
Author: Szilárd Pfeiffer
Maintainer: Szilárd Pfeiffer
Maintainer-email: coroner@pfeifferszilard.hu
License: Apache-2.0
Keywords: dhe denial-of-service tls ssh
Classifier: Development Status :: 3 - Alpha
Classifier: Intended Audience :: Information Technology
Classifier: Intended Audience :: Science/Research
Classifier: Intended Audience :: System Administrators
Classifier: License :: OSI Approved :: Apache Software License
Classifier: Natural Language :: English
Classifier: Operating System :: MacOS
Classifier: Operating System :: Microsoft :: Windows
Classifier: Operating System :: POSIX
Classifier: Programming Language :: Python :: 3.6
Classifier: Programming Language :: Python :: 3.7
Classifier: Programming Language :: Python :: 3.8
Classifier: Programming Language :: Python :: 3.9
Classifier: Programming Language :: Python :: 3.10
Classifier: Programming Language :: Python :: 3.11
Classifier: Programming Language :: Python :: Implementation :: CPython
Classifier: Programming Language :: Python :: Implementation :: PyPy
Classifier: Programming Language :: Python
Classifier: Topic :: Security
Classifier: Topic :: Security :: Cryptography
Classifier: Topic :: Software Development :: Testing :: Traffic Generation
Classifier: Topic :: Software Development :: Testing
License-File: LICENSE.txt
Requires-Dist: attrs >=19.2.0
Requires-Dist: cryptolyzer ==0.12.1
Requires-Dist: urllib3
Provides-Extra: pep8
Requires-Dist: flake8 ; extra == 'pep8'
Provides-Extra: pylint
Requires-Dist: pylint ; extra == 'pylint'
Provides-Extra: test
Requires-Dist: unittest2 ; extra == 'test'
Requires-Dist: coverage ; extra == 'test'
Requires-Dist: six ; extra == 'test'
